azure_cli_batch_extensions-1.0.0-py3.5-nspkg.pth
azure/cli/command_modules/batch_extensions/__init__.py
azure/cli/command_modules/batch_extensions/_client_factory.py
azure/cli/command_modules/batch_extensions/_help.py
azure/cli/command_modules/batch_extensions/_params.py
azure/cli/command_modules/batch_extensions/_validators.py
azure/cli/command_modules/batch_extensions/commands.py
azure/cli/command_modules/batch_extensions/custom.py
azure/cli/command_modules/batch_extensions/version.py
azure_cli_batch_extensions-1.0.0.dist-info/DESCRIPTION.rst
azure_cli_batch_extensions-1.0.0.dist-info/METADATA
azure_cli_batch_extensions-1.0.0.dist-info/RECORD
azure_cli_batch_extensions-1.0.0.dist-info/WHEEL
azure_cli_batch_extensions-1.0.0.dist-info/metadata.json
azure_cli_batch_extensions-1.0.0.dist-info/namespace_packages.txt
azure_cli_batch_extensions-1.0.0.dist-info/top_level.txt
