Metadata-Version: 2.0
Name: azure-cli-batch-extensions
Version: 1.0.0
Summary: Microsoft Azure Command-Line Tools Extended Batch Command Module
Home-page: https://github.com/Azure/azure-batch-cli-extensions
Author: Microsoft Corporation
Author-email: askwabatch@microsoft.com
License: MIT
Requires-Dist: azure-batch (<4,>=3.1)
Requires-Dist: azure-batch-extensions (<1,>=0.2)
Requires-Dist: azure-cli-batch
Requires-Dist: azure-cli-core
Requires-Dist: azure-mgmt-batch (>=4.0,<5)
Requires-Dist: azure-mgmt-storage (>=1.0,<2)
Requires-Dist: azure-storage (>=0.34,<0.35)
Requires-Dist: msrestazure (>=0.4.11,<1)
Requires-Dist: pathlib (>=1.0.1); python_version<'3.4'
